flask_entra_auth/__init__.py
flask_entra_auth/exceptions.py
flask_entra_auth/mocks/__init__.py
flask_entra_auth/mocks/jwks.py
flask_entra_auth/mocks/jwt.py
flask_entra_auth/resource_protector.py
flask_entra_auth/token.py
flask_entra_auth-0.9.0.dist-info/LICENSE.md
flask_entra_auth-0.9.0.dist-info/METADATA
flask_entra_auth-0.9.0.dist-info/WHEEL
flask_entra_auth-0.9.0.dist-info/RECORD
