Metadata-Version: 2.1
Name: flask-entra-auth
Version: 0.9.0
Summary: Flask extension for authenticating and authorising requests using Entra identity platform.
License: MIT
Author: Felix Fennell
Author-email: felnne@bas.ac.uk
Requires-Python: >=3.9,<4.0
Classifier: License :: OSI Approved :: MIT License
Classifier: Programming Language :: Python :: 3
Classifier: Programming Language :: Python :: 3.9
Classifier: Programming Language :: Python :: 3.10
Classifier: Programming Language :: Python :: 3.11
Classifier: Programming Language :: Python :: 3.12
Requires-Dist: authlib (>=1.3.1,<2.0.0)
Requires-Dist: flask (>=2.3,<4.0)
Requires-Dist: joserfc (>=1.0.0,<2.0.0)
Requires-Dist: pyjwt[crypto] (>=2.9.0,<3.0.0)
Requires-Dist: requests (>=2.32.3,<3.0.0)
